
{
  "alarm" : 
  [
    
    {
      "ACTION" : "ACTIVATETASK",
      "ACTION_S" : 
      {
        "TASK" : "ReceiveSetSpeed"
      },
      "AUTOSTART" : "true",
      "AUTOSTART_S" : 
      {
        "ALARMTIME" : 100,
        "APPMODE" : 
        [
          
          {
            "VALUE" : "stdAppmode"
          }
        ],
        "CYCLETIME" : 70
      },
      "COUNTER" : "SystemCounter",
      "NAME" : "periodicAlarm1"
    },    
    {
      "ACTION" : "ACTIVATETASK",
      "ACTION_S" : 
      {
        "TASK" : "SendCANM1"
      },
      "AUTOSTART" : "true",
      "AUTOSTART_S" : 
      {
        "ALARMTIME" : 300,
        "APPMODE" : 
        [
          
          {
            "VALUE" : "stdAppmode"
          }
        ],
        "CYCLETIME" : 100
      },
      "COUNTER" : "SystemCounter",
      "NAME" : "periodicAlarm2"
    },    
    {
      "ACTION" : "ACTIVATETASK",
      "ACTION_S" : 
      {
        "TASK" : "AccOnOff"
      },
      "AUTOSTART" : "true",
      "AUTOSTART_S" : 
      {
        "ALARMTIME" : 500,
        "APPMODE" : 
        [
          
          {
            "VALUE" : "stdAppmode"
          }
        ],
        "CYCLETIME" : 100
      },
      "COUNTER" : "SystemCounter",
      "NAME" : "periodicAlarm3"
    },    
    {
      "ACTION" : "ACTIVATETASK",
      "ACTION_S" : 
      {
        "TASK" : "SendCANM2"
      },
      "AUTOSTART" : "true",
      "AUTOSTART_S" : 
      {
        "ALARMTIME" : 500,
        "APPMODE" : 
        [
          
          {
            "VALUE" : "stdAppmode"
          }
        ],
        "CYCLETIME" : 70
      },
      "COUNTER" : "SystemCounter",
      "NAME" : "periodicAlarm4"
    },    
    {
      "ACTION" : "ACTIVATETASK",
      "ACTION_S" : 
      {
        "TASK" : "ReceiveCANM3"
      },
      "AUTOSTART" : "true",
      "AUTOSTART_S" : 
      {
        "ALARMTIME" : 100,
        "APPMODE" : 
        [
          
          {
            "VALUE" : "stdAppmode"
          }
        ],
        "CYCLETIME" : 50
      },
      "COUNTER" : "SystemCounter",
      "NAME" : "periodicAlarm5"
    },    
    {
      "ACTION" : "ACTIVATETASK",
      "ACTION_S" : 
      {
        "TASK" : "ReceiveCANM4"
      },
      "AUTOSTART" : "true",
      "AUTOSTART_S" : 
      {
        "ALARMTIME" : 50,
        "APPMODE" : 
        [
          
          {
            "VALUE" : "stdAppmode"
          }
        ],
        "CYCLETIME" : 20
      },
      "COUNTER" : "SystemCounter",
      "NAME" : "periodicAlarm6"
    },    
    {
      "ACTION" : "ACTIVATETASK",
      "ACTION_S" : 
      {
        "TASK" : "ReceiveCANM5"
      },
      "AUTOSTART" : "true",
      "AUTOSTART_S" : 
      {
        "ALARMTIME" : 500,
        "APPMODE" : 
        [
          
          {
            "VALUE" : "stdAppmode"
          }
        ],
        "CYCLETIME" : 100
      },
      "COUNTER" : "SystemCounter",
      "NAME" : "periodicAlarm7"
    }
  ],
  "event" : [],
  "ioc" : [],
  "isr" : [],
  "message" : [],
  "resource" : 
  [
    
    {
      "ISRUSAGE" : [],
      "KIND" : "Resource",
      "NAME" : "res1",
      "PRIORITY" : 1,
      "RESOURCEPROPERTY" : "STANDARD",
      "TASKUSAGE" : []
    }
  ],
  "task" : 
  [
    
    {
      "ACTIVATION" : 1,
      "AUTOSTART" : "false",
      "KIND" : "Task",
      "NAME" : "SendCANM2",
      "NONPREEMPTABLE" : "false",
      "PRIORITY" : 2,
      "SCHEDULE" : "FULL",
      "STACKSIZE" : 128,
      "USEINTERNALRESOURCE" : "false"
    },    
    {
      "ACTIVATION" : 1,
      "AUTOSTART" : "false",
      "KIND" : "Task",
      "NAME" : "ReceiveCANM4",
      "NONPREEMPTABLE" : "false",
      "PRIORITY" : 2,
      "SCHEDULE" : "FULL",
      "STACKSIZE" : 128,
      "USEINTERNALRESOURCE" : "false"
    },    
    {
      "ACTIVATION" : 1,
      "AUTOSTART" : "false",
      "KIND" : "Task",
      "NAME" : "ReceiveCANM5",
      "NONPREEMPTABLE" : "false",
      "PRIORITY" : 3,
      "SCHEDULE" : "FULL",
      "STACKSIZE" : 128,
      "USEINTERNALRESOURCE" : "false"
    },    
    {
      "ACTIVATION" : 1,
      "AUTOSTART" : "false",
      "KIND" : "Task",
      "NAME" : "AccOnOff",
      "NONPREEMPTABLE" : "false",
      "PRIORITY" : 3,
      "SCHEDULE" : "FULL",
      "STACKSIZE" : 128,
      "USEINTERNALRESOURCE" : "false"
    },    
    {
      "ACTIVATION" : 1,
      "AUTOSTART" : "false",
      "KIND" : "Task",
      "NAME" : "ReceiveSetSpeed",
      "NONPREEMPTABLE" : "false",
      "PRIORITY" : 3,
      "SCHEDULE" : "FULL",
      "STACKSIZE" : 128,
      "USEINTERNALRESOURCE" : "false"
    },    
    {
      "ACTIVATION" : 1,
      "AUTOSTART" : "false",
      "KIND" : "Task",
      "NAME" : "SendCANM1",
      "NONPREEMPTABLE" : "false",
      "PRIORITY" : 4,
      "SCHEDULE" : "FULL",
      "STACKSIZE" : 128,
      "USEINTERNALRESOURCE" : "false"
    },    
    {
      "ACTIVATION" : 1,
      "AUTOSTART" : "false",
      "KIND" : "Task",
      "NAME" : "ReceiveCANM3",
      "NONPREEMPTABLE" : "false",
      "PRIORITY" : 5,
      "SCHEDULE" : "FULL",
      "STACKSIZE" : 128,
      "USEINTERNALRESOURCE" : "false"
    }
  ]
}